feng_hirst_parser/__init__.py
feng_hirst_parser/example.py
feng_hirst_parser/example.txt
feng_hirst_parser/parse.py
feng_hirst_parser/parser_wrapper.py
feng_hirst_parser/requirements.txt
feng_hirst_parser/sanity_check.py
feng_hirst_parser/test_feng.py
feng_hirst_parser/__pycache__/__init__.cpython-311.pyc
feng_hirst_parser/__pycache__/example.cpython-311.pyc
feng_hirst_parser/__pycache__/parse.cpython-311.pyc
feng_hirst_parser/classifiers/__init__.py
feng_hirst_parser/classifiers/crf_classifier.py
feng_hirst_parser/classifiers/__pycache__/__init__.cpython-311.pyc
feng_hirst_parser/classifiers/__pycache__/crf_classifier.cpython-311.pyc
feng_hirst_parser/document/__init__.py
feng_hirst_parser/document/base_representation.py
feng_hirst_parser/document/constituent.py
feng_hirst_parser/document/dependency.py
feng_hirst_parser/document/doc.py
feng_hirst_parser/document/sentence.py
feng_hirst_parser/document/token.py
feng_hirst_parser/document/__pycache__/__init__.cpython-311.pyc
feng_hirst_parser/document/__pycache__/base_representation.cpython-311.pyc
feng_hirst_parser/document/__pycache__/constituent.cpython-311.pyc
feng_hirst_parser/document/__pycache__/dependency.cpython-311.pyc
feng_hirst_parser/document/__pycache__/doc.cpython-311.pyc
feng_hirst_parser/document/__pycache__/sentence.cpython-311.pyc
feng_hirst_parser/document/__pycache__/token.cpython-311.pyc
feng_hirst_parser/features/__init__.py
feng_hirst_parser/features/segmenter_feature_writer.py
feng_hirst_parser/features/tree_feature_writer.py
feng_hirst_parser/features/__pycache__/__init__.cpython-311.pyc
feng_hirst_parser/features/__pycache__/segmenter_feature_writer.cpython-311.pyc
feng_hirst_parser/features/__pycache__/tree_feature_writer.cpython-311.pyc
feng_hirst_parser/logs/__init__.py
feng_hirst_parser/logs/log_writer.py
feng_hirst_parser/logs/__pycache__/__init__.cpython-311.pyc
feng_hirst_parser/logs/__pycache__/log_writer.cpython-311.pyc
feng_hirst_parser/model/seg_set_CRF/seg.crfsuite
feng_hirst_rst_parser-0.1.4.dist-info/LICENSE
feng_hirst_rst_parser-0.1.4.dist-info/METADATA
feng_hirst_rst_parser-0.1.4.dist-info/WHEEL
feng_hirst_rst_parser-0.1.4.dist-info/top_level.txt
feng_hirst_rst_parser-0.1.4.dist-info/RECORD
