Metadata-Version: 2.1
Name: feng-hirst-rst-parser
Version: 0.1.4
Summary: Implementation of the Feng-Hirst RST Discourse Parser
Home-page: https://github.com/ThHuberSG/feng-hirst-rst-parser
Author: Thomas Huber
Author-email: thomas.huber@unisg.ch
License: BSD-3-Clause
Project-URL: Bug Tracker, https://github.com/ThHuberSG/feng-hirst-rst-parser/issues
Project-URL: Documentation, https://github.com/ThHuberSG/feng-hirst-rst-parser/wiki
Keywords: RST discourse parsing,computational linguistics,NLP,Feng-Hirst
Classifier: License :: OSI Approved :: BSD License
Classifier: Programming Language :: Python :: 3
Classifier: Programming Language :: Python :: 3.7
Classifier: Programming Language :: Python :: 3.8
Classifier: Programming Language :: Python :: 3.9
Classifier: Programming Language :: Python :: 3.10
Classifier: Programming Language :: Python :: 3.11
Requires-Python: >=3.7
License-File: LICENSE
Requires-Dist: networkx==3.4.2
Requires-Dist: nltk==3.9.1
Requires-Dist: pytest==8.3.3
